ccaconfig/__init__.py
ccaconfig/config.py
ccaconfig/errors.py
ccaconfig-0.4.0.dist-info/METADATA
ccaconfig-0.4.0.dist-info/WHEEL
ccaconfig-0.4.0.dist-info/RECORD
