Metadata-Version: 2.1
Name: ccaconfig
Version: 0.4.0
Summary: Easily find and read application configuration files.
Home-page: https://github.com/ccdale/ccaconfig
License: GPL-3.0-or-later
Author: Chris Allison
Author-email: chris.charles.allison@gmail.com
Requires-Python: >=3.9,<4.0
Classifier: License :: OSI Approved :: GNU General Public License v3 or later (GPLv3+)
Classifier: Programming Language :: Python :: 3
Classifier: Programming Language :: Python :: 3.9
Classifier: Programming Language :: Python :: 3.10
Classifier: Programming Language :: Python :: 3.11
Classifier: Programming Language :: Python :: 3.12
Requires-Dist: ccalogging (>=0.5.3,<0.6.0)
Requires-Dist: pyyaml (>=6.0,<7.0)
Project-URL: Repository, https://github.com/ccdale/ccaconfig
